bkflow_dmn/__init__.py
bkflow_dmn/__version__.py
bkflow_dmn/api.py
bkflow_dmn/data_model.py
bkflow_dmn/exception.py
bkflow_dmn/hit_policy.py
bkflow_dmn-0.2.0.dist-info/WHEEL
bkflow_dmn-0.2.0.dist-info/METADATA
bkflow_dmn-0.2.0.dist-info/RECORD
