Metadata-Version: 2.1
Name: bkflow-dmn
Version: 0.2.0
Summary: A DMN (Decision Model and Notation) Implementation for Python
Author-email: normal-wls <weishi.swee@qq.com>
Requires-Dist: bkflow-feel >= 1.0.0,<2
Requires-Dist: pydantic <3
Requires-Dist: pytest >=7.0.1,<8 ; extra == "test"
Requires-Dist: pytest-benchmark[histogram] >=3.4.1,<4 ; extra == "test"
Project-URL: Home, https://github.com/TencentBlueKing/bkflow-dmn
Provides-Extra: test
